{
    "p2kwiet168597368520138_btnDisplayPrevious_onClick_seq0": {
        "id": "p2kwiet168597368520138_btnDisplayPrevious_onClick_seq0",
        "type": "ACTION_SEQUENCE",
        "params": [{
            "name": "eventobject",
            "value": "eventobject"
        }],
        "language": "js",
        "actions": [{
            "id": "expression_onClick_62466850822901753",
            "type": "ADD_SNIPPET",
            "codeSnippet": "equipmentOrderVerify.onDisplayPreviousClick();"
        }]
    }
}