{
    "p2kwiet168597368520680_segPrintTexts_onRowClick_seq0": {
        "id": "p2kwiet168597368520680_segPrintTexts_onRowClick_seq0",
        "type": "ACTION_SEQUENCE",
        "params": [{
            "name": "eventobject",
            "value": "eventobject"
        }, {
            "name": "sectionNumber",
            "value": "sectionNumber"
        }, {
            "name": "rowNumber",
            "value": "rowNumber"
        }, {
            "name": "selectedState",
            "value": "selectedState"
        }],
        "language": "js",
        "actions": [{
            "id": "expression_onRowClick_130306850822902641",
            "type": "ADD_SNIPPET",
            "codeSnippet": "partialQuotationPrintText.onPrintTextSelection(rowNumber);"
        }]
    }
}